wela_agents/__init__.py
wela_agents/agents/__init__.py
wela_agents/agents/agent.py
wela_agents/agents/conversation.py
wela_agents/agents/llm.py
wela_agents/agents/meta.py
wela_agents/agents/sequential.py
wela_agents/agents/workflow.py
wela_agents/callback/__init__.py
wela_agents/callback/callback.py
wela_agents/callback/event.py
wela_agents/embedding/__init__.py
wela_agents/embedding/embedding.py
wela_agents/embedding/openai_embedding.py
wela_agents/embedding/text_embedding.py
wela_agents/memory/__init__.py
wela_agents/memory/buffer_memory.py
wela_agents/memory/memory.py
wela_agents/memory/qdrant_memory.py
wela_agents/memory/window_buffer_memory.py
wela_agents/models/__init__.py
wela_agents/models/model.py
wela_agents/models/openai_chat.py
wela_agents/reranker/__init__.py
wela_agents/reranker/reranker.py
wela_agents/reranker/siliconflow_reranker.py
wela_agents/reranker/text_reranker.py
wela_agents/retriever/__init__.py
wela_agents/retriever/qdrant_retriever.py
wela_agents/retriever/retriever.py
wela_agents/schema/__init__.py
wela_agents/schema/document/__init__.py
wela_agents/schema/document/document.py
wela_agents/schema/prompt/__init__.py
wela_agents/schema/prompt/openai_chat.py
wela_agents/schema/template/__init__.py
wela_agents/schema/template/openai_chat.py
wela_agents/schema/template/prompt_template.py
wela_agents/toolkit/__init__.py
wela_agents/toolkit/tool.py
wela_agents/toolkit/tool_result.py
wela_agents/toolkit/toolkit.py
wela_agents-0.0.20.dist-info/LICENSE
wela_agents-0.0.20.dist-info/METADATA
wela_agents-0.0.20.dist-info/WHEEL
wela_agents-0.0.20.dist-info/top_level.txt
wela_agents-0.0.20.dist-info/RECORD
