Metadata-Version: 2.1
Name: wela_agents
Version: 0.0.20
Summary: An agent framework for Wela
Home-page: https://github.com/lewiswu1209/wela_agents.git
Author: Lewis Wu
Author-email: lewiswu1209@163.com
License: MIT
License-File: LICENSE
Requires-Dist: torch
Requires-Dist: addict
Requires-Dist: openai
Requires-Dist: pillow
Requires-Dist: datasets <3.4.0
Requires-Dist: curl-cffi
Requires-Dist: modelscope
Requires-Dist: simplejson
Requires-Dist: transformers ==4.48.3
Requires-Dist: qdrant-client
Requires-Dist: huggingface-hub ==0.25.*
Requires-Dist: sortedcontainers
